django_templateaddons3-1.0.dist-info/DESCRIPTION.rst
django_templateaddons3-1.0.dist-info/METADATA
django_templateaddons3-1.0.dist-info/RECORD
django_templateaddons3-1.0.dist-info/WHEEL
django_templateaddons3-1.0.dist-info/metadata.json
django_templateaddons3-1.0.dist-info/top_level.txt
templateaddons/__init__.py
templateaddons/__init__.pyc
templateaddons/context_processors.py
templateaddons/models.py
templateaddons/models.pyc
templateaddons/settings.py
templateaddons/settings.pyc
templateaddons/test_runner.py
templateaddons/test_runner.pyc
templateaddons/test_settings.py
templateaddons/test_settings.pyc
templateaddons/tests.py
templateaddons/tests.pyc
templateaddons/utils.py
templateaddons/utils.pyc
templateaddons/__pycache__/__init__.cpython-35.pyc
templateaddons/__pycache__/models.cpython-35.pyc
templateaddons/__pycache__/settings.cpython-35.pyc
templateaddons/__pycache__/test_runner.cpython-35.pyc
templateaddons/__pycache__/test_settings.cpython-35.pyc
templateaddons/__pycache__/tests.cpython-35.pyc
templateaddons/__pycache__/utils.cpython-35.pyc
templateaddons/templates/tests/templateaddons/javascript/base.html
templateaddons/templates/tests/templateaddons/javascript/home.html
templateaddons/templates/tests/templateaddons/javascript/menu.html
templateaddons/templatetags/__init__.py
templateaddons/templatetags/__init__.pyc
templateaddons/templatetags/assign.py
templateaddons/templatetags/assign.pyc
templateaddons/templatetags/counter.py
templateaddons/templatetags/counter.pyc
templateaddons/templatetags/heading.py
templateaddons/templatetags/heading.pyc
templateaddons/templatetags/javascript.py
templateaddons/templatetags/javascript.pyc
templateaddons/templatetags/replace.py
templateaddons/templatetags/replace.pyc
templateaddons/templatetags/__pycache__/__init__.cpython-35.pyc
templateaddons/templatetags/__pycache__/assign.cpython-35.pyc
templateaddons/templatetags/__pycache__/counter.cpython-35.pyc
templateaddons/templatetags/__pycache__/heading.cpython-35.pyc
templateaddons/templatetags/__pycache__/javascript.cpython-35.pyc
templateaddons/templatetags/__pycache__/replace.cpython-35.pyc
