Metadata-Version: 2.0
Name: django-templateaddons3
Version: 1.0
Summary: A set of tools for use with templates of the Django framework: additional template tags, context processors and utilities for template tag development.
Home-page: https://github.com/django-templateaddons/django-templateaddons3
Author: django-templateaddons
Author-email: django-templateaddons@github.com
License: BSD
Download-URL: https://github.com/django-templateaddons/django-templateaddons3/releases
Platform: Any
Classifier: Development Status :: 5 - Production/Stable
Classifier: Environment :: Web Environment
Classifier: Intended Audience :: Developers
Classifier: License :: OSI Approved :: BSD License
Classifier: Operating System :: OS Independent
Classifier: Programming Language :: Python
Classifier: Framework :: Django
Classifier: Programming Language :: Python :: 2.7
Classifier: Programming Language :: Python :: 3.3
Classifier: Programming Language :: Python :: 3.4
Classifier: Programming Language :: Python :: 3.5
Classifier: Programming Language :: JavaScript
Classifier: Topic :: Internet :: WWW/HTTP :: Site Management
Requires-Dist: Django (>=1.8)
